{
  "_id": "",
  "courseId": "basic-course",
  "courseName": "בניית אתרי אינטרנט בסיסי",
  "courseContent": [
    {
      "module": 1,
      "title": "הקדמה",
      "lessons": [
        {
          "lessonId": "1.1",
          "title": "אודות הקורס",
          "sections": [
            {
              "sectionTitle": "מה נלמד בקורס",
              "textBlock": ["פסקה ראשונה", "פסקה שנייה", "פסקה שלישית"],
              "image": {
                "url": "image1Url.png",
                "altText": "Image1",
                "descText": "Image desc",
                "width": [100, 400]
              },
              "codeBox": {
                "codeLang": "JS",
                "lines": [
                  {
                    "element": "<body dir='rtl'>",
                    "spaces": 0,
                    "color": "white"
                  },
                  { "element": "<table>", "spaces": 2, "color": "red.300" },
                  {
                    "element": "<caption>סוגי פירות וירקות</caption>",
                    "spaces": 4,
                    "color": "orange.300"
                  }
                ]
              }
            },
            {
              "sectionTitle": "גלריית תמונות",
              "imagesGallery": [
                {
                  "url": "image3Url.png",
                  "altText": "Image 3",
                  "descText": "Image 3 desc"
                },
                {
                  "url": "image4Url.png",
                  "altText": "Image 4",
                  "descText": "Image 4 desc"
                }
              ],
              "listBlock": ["פריט 1", "פריט 2"]
            },
            {
              "sectionTitle": "עם מה נצא מהקורס?",
              "textBlock": ["פסקה רביעית", "פסקה חמישית", "פסקה שישית"],
              "image": {
                "url": "image2url",
                "altText": "Image 2",
                "descText": "Image 2 desc",
                "width": [100, 300]
              },
              "frameClause": {
                "frameTitle": "אבג",
                "paragraphs": ["פסקה 1", "פסקה 2"]
              }
            }
          ]
        },
        {
          "lessonId": "1.2",
          "title": "מה זה אינטרנט?",
          "sections": [{ "sectionTitle": "אינטרנט?" }]
        },
        {
          "lessonId": "1.3",
          "title": "עורכי קוד (Text Editors)"
        },
        {
          "lessonId": "1.4",
          "title": "סביבות עבודה: Git & GitHub"
        }
      ]
    },
    {
      "module": 2,
      "title": "HTML",
      "lessons": [
        {
          "lessonId": "2.1",
          "title": "המבנה האנטומי של עמוד HTML"
        },
        {
          "lessonId": "2.2",
          "title": "רכיבים מילוליים: כותרות, פסקאות ורשימות (Headings, Paragraphs & Lists)"
        },
        {
          "lessonId": "2.3",
          "title": "חיבורים בין עולמות וקישורים (Links)"
        },
        {
          "lessonId": "2.4",
          "title": "יצירת טבלה (Tables)"
        },
        {
          "lessonId": "2.5",
          "title": "יצירת טפסים (Forms)"
        },
        {
          "lessonId": "2.6",
          "title": "אובייקטים חזותיים: תמונות ווידאו (Images & Videos)"
        },
        {
          "lessonId": "2.7",
          "title": "מבנה העמוד וסמנטיקה (Semantics Boxes with HTML5)"
        },
        {
          "lessonId": "2.8",
          "title": "מידע על העמוד ו-Meta Data"
        },
        {
          "lessonId": "2.9",
          "title": "תרגיל מסכם"
        }
      ]
    },
    {
      "module": 3,
      "title": "CSS",
      "lessons": [
        {
          "lessonId": "3.1",
          "title": "מה זה CSS, ועל מה הוא אחראי בבניית אתרי אינטרנט?"
        },
        {
          "lessonId": "3.2",
          "title": "הגדרות כלליות של CSS."
        },
        {
          "lessonId": "3.3",
          "title": "מאפייני עיצוב בסיסיים"
        }
      ]
    },
    {
      "module": 4,
      "title": "Java Script",
      "lessons": [
        { "lessonId": "4.1", "title": "מבוא ל-Java Script" },
        { "lessonId": "4.2", "title": "שיעור 2" },
        { "lessonId": "4.3", "title": "שיעור 3" }
      ]
    },
    {
      "module": 5,
      "title": "פרויקט סיום",
      "lessons": [
        {
          "lessonId": "5.1",
          "title": "בחירת נושא לפרויקט"
        },
        {
          "lessonId": "5.2",
          "title": "תכנון הפרויקט"
        },
        {
          "lessonId": "5.3",
          "title": "ביצוע הפרויקט"
        }
      ]
    },
    {
      "module": 6,
      "title": "משוב על הקורס",
      "lessons": [
        {
          "lessonId": "6.1",
          "title": "תן דעתך על הקורס"
        },
        {
          "lessonId": "6.2",
          "title": "רמת הקושי של הקורס"
        },
        {
          "lessonId": "6.3",
          "title": "מידת העניין בקורס"
        }
      ]
    }
  ]
}
